py_sdk_pkg/__init__.py
py_sdk_nocodeapi-0.0.1.dist-info/LICENSE
py_sdk_nocodeapi-0.0.1.dist-info/METADATA
py_sdk_nocodeapi-0.0.1.dist-info/WHEEL
py_sdk_nocodeapi-0.0.1.dist-info/top_level.txt
py_sdk_nocodeapi-0.0.1.dist-info/RECORD
