Metadata-Version: 2.1
Name: py-sdk-nocodeapi
Version: 0.0.1
Summary: An SDK for nocodeapi.net
Home-page: https://bitbucket.org/zeusakm/py_sdk
Author: Arthur Kushman
Author-email: arthurkushman@gmail.com
License: UNKNOWN
Platform: UNKNOWN
Classifier: Programming Language :: Python :: 3
Classifier: License :: OSI Approved :: MIT License
Classifier: Operating System :: OS Independent
Requires-Python: >=3.6
